MANIFEST.in
setup.py
etc/colab/plugins.d/pauta.py
etc/colab/widgets.d/pauta_widgets.py
src/colab_pauta/__init__.py
src/colab_pauta/apps.py
src/colab_pauta/data_importer.py
src/colab_pauta/diazo.xml
src/colab_pauta/models.py
src/colab_pauta/search_indexes.py
src/colab_pauta/tasks.py
src/colab_pauta/urls.py
src/colab_pauta/views.py
src/colab_pauta.egg-info/PKG-INFO
src/colab_pauta.egg-info/SOURCES.txt
src/colab_pauta.egg-info/dependency_links.txt
src/colab_pauta.egg-info/not-zip-safe
src/colab_pauta.egg-info/requires.txt
src/colab_pauta.egg-info/top_level.txt
src/colab_pauta/management/__init__.py
src/colab_pauta/management/commands/__init__.py
src/colab_pauta/management/commands/fetch_data_pautas.py
src/colab_pauta/migrations/0001_initial.py
src/colab_pauta/migrations/0002_auto_20170825_1649.py
src/colab_pauta/migrations/__init__.py
src/colab_pauta/static/js/edem-pauta-plugin.js
src/colab_pauta/static/scss/overrides-pauta.scss
src/colab_pauta/templates/proxy/pauta.html
src/colab_pauta/templates/widgets/pauta_home_section.html
src/colab_pauta/templates/widgets/pauta_navigation_links.html
src/colab_pauta/widgets/__init__.py
src/colab_pauta/widgets/home_section.py
src/colab_pauta/widgets/navigation_links.py