Metadata-Version: 1.1
Name: colab-pauta
Version: 0.3.0
Summary: Colab Pauta plugin
Home-page: https://github.com/labhackercd/colab-pauta-plugin
Author: labhackercd
Author-email: labhackercd@gmail.com
License: GPLv3
Platform: UNKNOWN
Classifier: Framework :: Django
Classifier: Intended Audience :: Developers
Classifier: Intended Audience :: System Administrators
Classifier: Operating System :: OS Independent
Classifier: Topic :: Software Development
